{
    "2018": {
        "Depreciation & Amortization": 43000.0,
        "Stock-based compensation": 6410000.0,
        "Operating Cash Flow": -4511000.0,
        "Capital Expenditure": -79000.0,
        "Acquisitions and disposals": 0.0,
        "Investment purchases and sales": -3626000.0,
        "Investing Cash flow": -3705000.0,
        "Issuance (repayment) of debt": -449000.0,
        "Issuance (buybacks) of shares": 11099000.0,
        "Dividend payments": 0.0,
        "Financing Cash Flow": 9529000.0,
        "Effect of forex changes on cash": 0.0,
        "Net cash flow / Change in cash": 1313000.0,
        "Free Cash Flow": -4590000.0,
        "Net Cash/Marketcap": 0.3189
    },
    "2017": {
        "Depreciation & Amortization": 19000.0,
        "Stock-based compensation": 15039000.0,
        "Operating Cash Flow": -5578000.0,
        "Capital Expenditure": -114000.0,
        "Acquisitions and disposals": 0.0,
        "Investment purchases and sales": -500000.0,
        "Investing Cash flow": -614000.0,
        "Issuance (repayment) of debt": -3106000.0,
        "Issuance (buybacks) of shares": 12550000.0,
        "Dividend payments": 0.0,
        "Financing Cash Flow": 7700000.0,
        "Effect of forex changes on cash": 0.0,
        "Net cash flow / Change in cash": 1508000.0,
        "Free Cash Flow": -5692000.0,
        "Net Cash/Marketcap": 0.0039
    },
    "2016": {
        "Depreciation & Amortization": 13000.0,
        "Stock-based compensation": 7565000.0,
        "Operating Cash Flow": -2908000.0,
        "Capital Expenditure": -411000.0,
        "Acquisitions and disposals": 0.0,
        "Investment purchases and sales": -460000.0,
        "Investing Cash flow": -871000.0,
        "Issuance (repayment) of debt": 1034000.0,
        "Issuance (buybacks) of shares": 134000.0,
        "Dividend payments": 0.0,
        "Financing Cash Flow": 180000.0,
        "Effect of forex changes on cash": 0.0,
        "Net cash flow / Change in cash": -3599000.0,
        "Free Cash Flow": -3319000.0,
        "Net Cash/Marketcap": -0.0081
    },
    "2015": {
        "Depreciation & Amortization": 7000.0,
        "Stock-based compensation": 3035000.0,
        "Operating Cash Flow": -2103000.0,
        "Capital Expenditure": -3000.0,
        "Acquisitions and disposals": 0.0,
        "Investment purchases and sales": -110000.0,
        "Investing Cash flow": -113000.0,
        "Issuance (repayment) of debt": 4653000.0,
        "Issuance (buybacks) of shares": 1982000.0,
        "Dividend payments": 0.0,
        "Financing Cash Flow": 6635000.0,
        "Effect of forex changes on cash": 0.0,
        "Net cash flow / Change in cash": 4419000.0,
        "Free Cash Flow": -2106000.0,
        "Net Cash/Marketcap": -0.0081
    },
    "2013": {
        "Depreciation & Amortization": 4895.0,
        "Stock-based compensation": 176400.0,
        "Operating Cash Flow": -1426059.0,
        "Capital Expenditure": -31260.0,
        "Acquisitions and disposals": 0.0,
        "Investment purchases and sales": 0.0,
        "Investing Cash flow": -36872.0,
        "Issuance (repayment) of debt": 88100.0,
        "Issuance (buybacks) of shares": 1367250.0,
        "Dividend payments": 0.0,
        "Financing Cash Flow": 1455350.0,
        "Effect of forex changes on cash": 0.0,
        "Net cash flow / Change in cash": -7581.0,
        "Free Cash Flow": -1457319.0,
        "Net Cash/Marketcap": -0.0081
    },
    "2012": {
        "Depreciation & Amortization": 0.0,
        "Stock-based compensation": 0.0,
        "Operating Cash Flow": -238530.0,
        "Capital Expenditure": -2722.0,
        "Acquisitions and disposals": 0.0,
        "Investment purchases and sales": 0.0,
        "Investing Cash flow": -7512.0,
        "Issuance (repayment) of debt": 0.0,
        "Issuance (buybacks) of shares": 297260.0,
        "Dividend payments": 0.0,
        "Financing Cash Flow": 297260.0,
        "Effect of forex changes on cash": 0.0,
        "Net cash flow / Change in cash": 51218.0,
        "Free Cash Flow": -241252.0,
        "Net Cash/Marketcap": -0.0081
    }
}