{
    "2019": {
        "Cash and cash equivalents": 188495000.0,
        "Short-term investments": 980000.0,
        "Cash and short-term investments": 189475000.0,
        "Receivables": 146113000.0,
        "Inventories": 145278000.0,
        "Total current assets": 508556000.0,
        "Property, Plant & Equipment Net": 276818000.0,
        "Goodwill and Intangible Assets": 1464115000.0,
        "Long-term investments": 0.0,
        "Tax assets": 6566000.0,
        "Total non-current assets": 1753210000.0,
        "Total assets": 2261766000.0,
        "Payables": 54529000.0,
        "Short-term debt": 13313000.0,
        "Total current liabilities": 171460000.0,
        "Long-term debt": 928463000.0,
        "Total debt": 941776000.0,
        "Deferred revenue": 5008000.0,
        "Tax Liabilities": 15725000.0,
        "Deposit Liabilities": 0.0,
        "Total non-current liabilities": 1111059000.0,
        "Total liabilities": 1281389000.0,
        "Other comprehensive income": 542074000.0,
        "Retained earnings (deficit)": 461501000.0,
        "Total shareholders equity": 980377000.0,
        "Investments": 980000.0,
        "Net Debt": 753281000.0,
        "Other Assets": 0.0,
        "Other Liabilities": 0.0
    },
    "2018": {
        "Cash and cash equivalents": 352921000.0,
        "Short-term investments": 0.0,
        "Cash and short-term investments": 352921000.0,
        "Receivables": 75886000.0,
        "Inventories": 71926000.0,
        "Total current assets": 522781000.0,
        "Property, Plant & Equipment Net": 111403000.0,
        "Goodwill and Intangible Assets": 136285000.0,
        "Long-term investments": 0.0,
        "Tax assets": 5840000.0,
        "Total non-current assets": 258192000.0,
        "Total assets": 780973000.0,
        "Payables": 18171000.0,
        "Short-term debt": 0.0,
        "Total current liabilities": 101154000.0,
        "Long-term debt": 0.0,
        "Total debt": 0.0,
        "Deferred revenue": 4894000.0,
        "Tax Liabilities": 18045000.0,
        "Deposit Liabilities": 0.0,
        "Total non-current liabilities": 13127000.0,
        "Total liabilities": 114281000.0,
        "Other comprehensive income": 190444000.0,
        "Retained earnings (deficit)": 471673000.0,
        "Total shareholders equity": 666692000.0,
        "Investments": 0.0,
        "Net Debt": -352921000.0,
        "Other Assets": 0.0,
        "Other Liabilities": 0.0
    },
    "2017": {
        "Cash and cash equivalents": 397890000.0,
        "Short-term investments": 0.0,
        "Cash and short-term investments": 397890000.0,
        "Receivables": 64793000.0,
        "Inventories": 71873000.0,
        "Total current assets": 550982000.0,
        "Property, Plant & Equipment Net": 106361000.0,
        "Goodwill and Intangible Assets": 144642000.0,
        "Long-term investments": 0.0,
        "Tax assets": 21598000.0,
        "Total non-current assets": 283118000.0,
        "Total assets": 834100000.0,
        "Payables": 17624000.0,
        "Short-term debt": 10938000.0,
        "Total current liabilities": 91213000.0,
        "Long-term debt": 132997000.0,
        "Total debt": 143935000.0,
        "Deferred revenue": 1559000.0,
        "Tax Liabilities": 9717000.0,
        "Deposit Liabilities": 0.0,
        "Total non-current liabilities": 147850000.0,
        "Total liabilities": 239063000.0,
        "Other comprehensive income": 193172000.0,
        "Retained earnings (deficit)": 397881000.0,
        "Total shareholders equity": 595037000.0,
        "Investments": 0.0,
        "Net Debt": -253955000.0,
        "Other Assets": 0.0,
        "Other Liabilities": 0.0
    },
    "2016": {
        "Cash and cash equivalents": 287479000.0,
        "Short-term investments": 0.0,
        "Cash and short-term investments": 287479000.0,
        "Receivables": 62830000.0,
        "Inventories": 72123000.0,
        "Total current assets": 437091000.0,
        "Property, Plant & Equipment Net": 106496000.0,
        "Goodwill and Intangible Assets": 151115000.0,
        "Long-term investments": 0.0,
        "Tax assets": 20747000.0,
        "Total non-current assets": 290835000.0,
        "Total assets": 727926000.0,
        "Payables": 16834000.0,
        "Short-term debt": 7656000.0,
        "Total current liabilities": 65885000.0,
        "Long-term debt": 147657000.0,
        "Total debt": 155313000.0,
        "Deferred revenue": 782000.0,
        "Tax Liabilities": 7878000.0,
        "Deposit Liabilities": 0.0,
        "Total non-current liabilities": 164393000.0,
        "Total liabilities": 230278000.0,
        "Other comprehensive income": 157282000.0,
        "Retained earnings (deficit)": 330776000.0,
        "Total shareholders equity": 497648000.0,
        "Investments": 0.0,
        "Net Debt": -132166000.0,
        "Other Assets": 0.0,
        "Other Liabilities": 0.0
    },
    "2015": {
        "Cash and cash equivalents": 354190000.0,
        "Short-term investments": 0.0,
        "Cash and short-term investments": 354190000.0,
        "Receivables": 49405000.0,
        "Inventories": 70678000.0,
        "Total current assets": 494508000.0,
        "Property, Plant & Equipment Net": 93743000.0,
        "Goodwill and Intangible Assets": 45007000.0,
        "Long-term investments": 0.0,
        "Tax assets": 12212000.0,
        "Total non-current assets": 165966000.0,
        "Total assets": 660474000.0,
        "Payables": 15448000.0,
        "Short-term debt": 8750000.0,
        "Total current liabilities": 60644000.0,
        "Long-term debt": 155313000.0,
        "Total debt": 164063000.0,
        "Deferred revenue": 538000.0,
        "Tax Liabilities": 4276000.0,
        "Deposit Liabilities": 0.0,
        "Total non-current liabilities": 170866000.0,
        "Total liabilities": 231510000.0,
        "Other comprehensive income": 150933000.0,
        "Retained earnings (deficit)": 284088000.0,
        "Total shareholders equity": 428964000.0,
        "Investments": 0.0,
        "Net Debt": -190127000.0,
        "Other Assets": 0.0,
        "Other Liabilities": 0.0
    },
    "2014": {
        "Cash and cash equivalents": 284155000.0,
        "Short-term investments": 0.0,
        "Cash and short-term investments": 284155000.0,
        "Receivables": 60693000.0,
        "Inventories": 64979000.0,
        "Total current assets": 427993000.0,
        "Property, Plant & Equipment Net": 100821000.0,
        "Goodwill and Intangible Assets": 50408000.0,
        "Long-term investments": 1654000.0,
        "Tax assets": 11353000.0,
        "Total non-current assets": 173174000.0,
        "Total assets": 601167000.0,
        "Payables": 15304000.0,
        "Short-term debt": 8750000.0,
        "Total current liabilities": 55448000.0,
        "Long-term debt": 164063000.0,
        "Total debt": 172813000.0,
        "Deferred revenue": 1223000.0,
        "Tax Liabilities": 5448000.0,
        "Deposit Liabilities": 0.0,
        "Total non-current liabilities": 173717000.0,
        "Total liabilities": 229165000.0,
        "Other comprehensive income": 134773000.0,
        "Retained earnings (deficit)": 227942000.0,
        "Total shareholders equity": 372002000.0,
        "Investments": 1654000.0,
        "Net Debt": -111342000.0,
        "Other Assets": 0.0,
        "Other Liabilities": 0.0
    },
    "2013": {
        "Cash and cash equivalents": 226029000.0,
        "Short-term investments": 0.0,
        "Cash and short-term investments": 226029000.0,
        "Receivables": 54640000.0,
        "Inventories": 63786000.0,
        "Total current assets": 365712000.0,
        "Property, Plant & Equipment Net": 111985000.0,
        "Goodwill and Intangible Assets": 54091000.0,
        "Long-term investments": 1375000.0,
        "Tax assets": 10291000.0,
        "Total non-current assets": 188794000.0,
        "Total assets": 554506000.0,
        "Payables": 16663000.0,
        "Short-term debt": 10938000.0,
        "Total current liabilities": 67500000.0,
        "Long-term debt": 150937000.0,
        "Total debt": 161875000.0,
        "Deferred revenue": 458000.0,
        "Tax Liabilities": 6931000.0,
        "Deposit Liabilities": 0.0,
        "Total non-current liabilities": 159929000.0,
        "Total liabilities": 227429000.0,
        "Other comprehensive income": 128785000.0,
        "Retained earnings (deficit)": 180826000.0,
        "Total shareholders equity": 327077000.0,
        "Investments": 1375000.0,
        "Net Debt": -64154000.0,
        "Other Assets": 0.0,
        "Other Liabilities": 0.0
    },
    "2012": {
        "Cash and cash equivalents": 178459000.0,
        "Short-term investments": 0.0,
        "Cash and short-term investments": 178459000.0,
        "Receivables": 53506000.0,
        "Inventories": 66472000.0,
        "Total current assets": 317888000.0,
        "Property, Plant & Equipment Net": 125020000.0,
        "Goodwill and Intangible Assets": 57093000.0,
        "Long-term investments": 1082000.0,
        "Tax assets": 5879000.0,
        "Total non-current assets": 199937000.0,
        "Total assets": 517825000.0,
        "Payables": 19542000.0,
        "Short-term debt": 2000.0,
        "Total current liabilities": 63219000.0,
        "Long-term debt": 19000.0,
        "Total debt": 21000.0,
        "Deferred revenue": 3341000.0,
        "Tax Liabilities": 2843000.0,
        "Deposit Liabilities": 0.0,
        "Total non-current liabilities": 13966000.0,
        "Total liabilities": 234234000.0,
        "Other comprehensive income": 123655000.0,
        "Retained earnings (deficit)": 129441000.0,
        "Total shareholders equity": 283591000.0,
        "Investments": 1082000.0,
        "Net Debt": -178438000.0,
        "Other Assets": 0.0,
        "Other Liabilities": 157049000.0
    },
    "2011": {
        "Cash and cash equivalents": 302546000.0,
        "Short-term investments": 0.0,
        "Cash and short-term investments": 302546000.0,
        "Receivables": 52747000.0,
        "Inventories": 56128000.0,
        "Total current assets": 430405000.0,
        "Property, Plant & Equipment Net": 130791000.0,
        "Goodwill and Intangible Assets": 55799000.0,
        "Long-term investments": 0.0,
        "Tax assets": 862000.0,
        "Total non-current assets": 197824000.0,
        "Total assets": 628229000.0,
        "Payables": 22436000.0,
        "Short-term debt": 10000.0,
        "Total current liabilities": 55550000.0,
        "Long-term debt": 2000.0,
        "Total debt": 12000.0,
        "Deferred revenue": 0.0,
        "Tax Liabilities": 808000.0,
        "Deposit Liabilities": 0.0,
        "Total non-current liabilities": 10574000.0,
        "Total liabilities": 61875000.0,
        "Other comprehensive income": 106770000.0,
        "Retained earnings (deficit)": 435429000.0,
        "Total shareholders equity": 566354000.0,
        "Investments": 0.0,
        "Net Debt": -302534000.0,
        "Other Assets": 0.0,
        "Other Liabilities": 0.0
    },
    "2010": {
        "Cash and cash equivalents": 254164000.0,
        "Short-term investments": 0.0,
        "Cash and short-term investments": 254164000.0,
        "Receivables": 57456000.0,
        "Inventories": 51896000.0,
        "Total current assets": 381029000.0,
        "Property, Plant & Equipment Net": 115811000.0,
        "Goodwill and Intangible Assets": 57525000.0,
        "Long-term investments": 0.0,
        "Tax assets": 8044000.0,
        "Total non-current assets": 190727000.0,
        "Total assets": 571756000.0,
        "Payables": 17521000.0,
        "Short-term debt": 1296000.0,
        "Total current liabilities": 53330000.0,
        "Long-term debt": 12000.0,
        "Total debt": 1308000.0,
        "Deferred revenue": 0.0,
        "Tax Liabilities": 0.0,
        "Deposit Liabilities": 0.0,
        "Total non-current liabilities": 7623000.0,
        "Total liabilities": 57413000.0,
        "Other comprehensive income": 112012000.0,
        "Retained earnings (deficit)": 383767000.0,
        "Total shareholders equity": 514343000.0,
        "Investments": 0.0,
        "Net Debt": -252856000.0,
        "Other Assets": 0.0,
        "Other Liabilities": 0.0
    },
    "2009": {
        "Cash and cash equivalents": 199952000.0,
        "Short-term investments": 0.0,
        "Cash and short-term investments": 199952000.0,
        "Receivables": 53538000.0,
        "Inventories": 44940000.0,
        "Total current assets": 198292000.0,
        "Property, Plant & Equipment Net": 122782000.0,
        "Goodwill and Intangible Assets": 58473000.0,
        "Long-term investments": 0.0,
        "Tax assets": 11947000.0,
        "Total non-current assets": 4879000.0,
        "Total assets": 515144000.0,
        "Payables": 15182000.0,
        "Short-term debt": 1210000.0,
        "Total current liabilities": 39536000.0,
        "Long-term debt": 1308000.0,
        "Total debt": 2518000.0,
        "Deferred revenue": 0.0,
        "Tax Liabilities": 0.0,
        "Deposit Liabilities": 0.0,
        "Total non-current liabilities": 4879000.0,
        "Total liabilities": 44415000.0,
        "Other comprehensive income": 13690000.0,
        "Retained earnings (deficit)": 334309000.0,
        "Total shareholders equity": 470729000.0,
        "Investments": 0.0,
        "Net Debt": -197434000.0,
        "Other Assets": 18422000.0,
        "Other Liabilities": 23144000.0
    }
}