{
    "2019": {
        "Revenue": 83412000.0,
        "Revenue Growth": 0.00694134263674445,
        "Cost of Revenue": 73960000.0,
        "Gross Profit": 9452000.0,
        "R&D Expenses": 3600000.0,
        "SG&A Expense": 20958000.0,
        "Operating Expenses": 24558000.0,
        "Operating Income": -15106000.0,
        "Interest Expense": 1502000.0,
        "Earnings before Tax": -16651000.0,
        "Income Tax Expense": 8000.0,
        "Net Income - Non-Controlling int": 0.0,
        "Net Income - Discontinued ops": 0.0,
        "Net Income": -16659000.0,
        "Preferred Dividends": 0.0,
        "Net Income Com": -16659000.0,
        "EPS": -0.25,
        "EPS Diluted": -0.25,
        "Weighted Average Shs Out": 66994000.0,
        "Weighted Average Shs Out (Dil)": 66994000.0,
        "Dividend per Share": 0.0,
        "Gross Margin": 0.113317028725,
        "EBITDA Margin": -0.162254831439,
        "EBIT Margin": -0.181101040618,
        "Profit Margin": -0.199719464825,
        "Free Cash Flow margin": -0.252517623364,
        "EBITDA": -13534000.0,
        "EBIT": -15106000.0,
        "Consolidated Income": -16659000.0,
        "Earnings Before Tax Margin": -0.199623555364,
        "Net Profit Margin": -0.199719464825
    },
    "2018": {
        "Revenue": 82837000.0,
        "Revenue Growth": 0.0734491829620703,
        "Cost of Revenue": 67856000.0,
        "Gross Profit": 14981000.0,
        "R&D Expenses": 4040000.0,
        "SG&A Expense": 19609000.0,
        "Operating Expenses": 23649000.0,
        "Operating Income": -8668000.0,
        "Interest Expense": 606000.0,
        "Earnings before Tax": -10008000.0,
        "Income Tax Expense": 18000.0,
        "Net Income - Non-Controlling int": 0.0,
        "Net Income - Discontinued ops": 0.0,
        "Net Income": -10026000.0,
        "Preferred Dividends": 0.0,
        "Net Income Com": -10026000.0,
        "EPS": -0.2,
        "EPS Diluted": -0.2,
        "Weighted Average Shs Out": 51339000.0,
        "Weighted Average Shs Out (Dil)": 51339000.0,
        "Dividend per Share": 0.0,
        "Gross Margin": 0.180849137463,
        "EBITDA Margin": -0.0880765841351,
        "EBIT Margin": -0.104639231261,
        "Profit Margin": -0.121032871784,
        "Free Cash Flow margin": -0.125463259172,
        "EBITDA": -7296000.0,
        "EBIT": -8668000.0,
        "Consolidated Income": -10026000.0,
        "Earnings Before Tax Margin": -0.12081557758,
        "Net Profit Margin": -0.121032871784
    },
    "2017": {
        "Revenue": 77169000.0,
        "Revenue Growth": -0.0943774864747509,
        "Cost of Revenue": 75380000.0,
        "Gross Profit": 1789000.0,
        "R&D Expenses": 5388000.0,
        "SG&A Expense": 20651000.0,
        "Operating Expenses": 26039000.0,
        "Operating Income": -24250000.0,
        "Interest Expense": 536000.0,
        "Earnings before Tax": -23902000.0,
        "Income Tax Expense": 19000.0,
        "Net Income - Non-Controlling int": 0.0,
        "Net Income - Discontinued ops": 0.0,
        "Net Income": -23921000.0,
        "Preferred Dividends": 0.0,
        "Net Income Com": -23921000.0,
        "EPS": -0.75,
        "EPS Diluted": -0.75,
        "Weighted Average Shs Out": 32074000.0,
        "Weighted Average Shs Out (Dil)": 32074000.0,
        "Dividend per Share": 0.0,
        "Gross Margin": 0.0231828843188,
        "EBITDA Margin": -0.291567857559,
        "EBIT Margin": -0.314245357592,
        "Profit Margin": -0.309981987586,
        "Free Cash Flow margin": -0.242973214633,
        "EBITDA": -22500000.0,
        "EBIT": -24250000.0,
        "Consolidated Income": -23921000.0,
        "Earnings Before Tax Margin": -0.309735774728,
        "Net Profit Margin": -0.309981987586
    },
    "2016": {
        "Revenue": 85211000.0,
        "Revenue Growth": -0.261993227150293,
        "Cost of Revenue": 72444000.0,
        "Gross Profit": 12767000.0,
        "R&D Expenses": 10152000.0,
        "SG&A Expense": 27106000.0,
        "Operating Expenses": 37258000.0,
        "Operating Income": -24491000.0,
        "Interest Expense": 640000.0,
        "Earnings before Tax": -25171000.0,
        "Income Tax Expense": 20000.0,
        "Net Income - Non-Controlling int": 0.0,
        "Net Income - Discontinued ops": 0.0,
        "Net Income": -25191000.0,
        "Preferred Dividends": 0.0,
        "Net Income Com": -25191000.0,
        "EPS": -1.39,
        "EPS Diluted": -1.39,
        "Weighted Average Shs Out": 18162000.0,
        "Weighted Average Shs Out (Dil)": 18162000.0,
        "Dividend per Share": 0.0,
        "Gross Margin": 0.14982807384,
        "EBITDA Margin": -0.264907112931,
        "EBIT Margin": -0.287415943951,
        "Profit Margin": -0.295630845783,
        "Free Cash Flow margin": -0.281454272336,
        "EBITDA": -22573000.0,
        "EBIT": -24491000.0,
        "Consolidated Income": -25191000.0,
        "Earnings Before Tax Margin": -0.295396134302,
        "Net Profit Margin": -0.295630845783
    },
    "2015": {
        "Revenue": 115461000.0,
        "Revenue Growth": -0.132557003869126,
        "Cost of Revenue": 97174000.0,
        "Gross Profit": 18287000.0,
        "R&D Expenses": 9679000.0,
        "SG&A Expense": 39517000.0,
        "Operating Expenses": 49196000.0,
        "Operating Income": -30909000.0,
        "Interest Expense": 548000.0,
        "Earnings before Tax": -31416000.0,
        "Income Tax Expense": 117000.0,
        "Net Income - Non-Controlling int": 0.0,
        "Net Income - Discontinued ops": 0.0,
        "Net Income": -31533000.0,
        "Preferred Dividends": 0.0,
        "Net Income Com": -31533000.0,
        "EPS": -0.1,
        "EPS Diluted": -0.1,
        "Weighted Average Shs Out": 328012000.0,
        "Weighted Average Shs Out (Dil)": 328012000.0,
        "Dividend per Share": 0.0,
        "Gross Margin": 0.158382484129,
        "EBITDA Margin": -0.251305635669,
        "EBIT Margin": -0.267700782082,
        "Profit Margin": -0.273105204355,
        "Free Cash Flow margin": -0.199357358762,
        "EBITDA": -29016000.0,
        "EBIT": -30909000.0,
        "Consolidated Income": -31533000.0,
        "Earnings Before Tax Margin": -0.272091875179,
        "Net Profit Margin": -0.273105204355
    },
    "2014": {
        "Revenue": 133105000.0,
        "Revenue Growth": 0.0434942809881073,
        "Cost of Revenue": 111409000.0,
        "Gross Profit": 21696000.0,
        "R&D Expenses": 9029000.0,
        "SG&A Expense": 27981000.0,
        "Operating Expenses": 37010000.0,
        "Operating Income": -15314000.0,
        "Interest Expense": 712000.0,
        "Earnings before Tax": -16036000.0,
        "Income Tax Expense": 220000.0,
        "Net Income - Non-Controlling int": 0.0,
        "Net Income - Discontinued ops": 0.0,
        "Net Income": -16256000.0,
        "Preferred Dividends": 0.0,
        "Net Income Com": -16256000.0,
        "EPS": -0.05,
        "EPS Diluted": -0.05,
        "Weighted Average Shs Out": 307060000.0,
        "Weighted Average Shs Out (Dil)": 307060000.0,
        "Dividend per Share": 0.0,
        "Gross Margin": 0.16299913602,
        "EBITDA Margin": -0.0959242703129,
        "EBIT Margin": -0.115052026596,
        "Profit Margin": -0.122129146163,
        "Free Cash Flow margin": -0.115938544758,
        "EBITDA": -12768000.0,
        "EBIT": -15314000.0,
        "Consolidated Income": -16256000.0,
        "Earnings Before Tax Margin": -0.120476315691,
        "Net Profit Margin": -0.122129146163
    },
    "2013": {
        "Revenue": 127557000.0,
        "Revenue Growth": 0.166278081026963,
        "Cost of Revenue": 113172000.0,
        "Gross Profit": 14385000.0,
        "R&D Expenses": 8979000.0,
        "SG&A Expense": 27364000.0,
        "Operating Expenses": 36343000.0,
        "Operating Income": -21958000.0,
        "Interest Expense": 717000.0,
        "Earnings before Tax": -21869000.0,
        "Income Tax Expense": 694000.0,
        "Net Income - Non-Controlling int": 0.0,
        "Net Income - Discontinued ops": 0.0,
        "Net Income": -22563000.0,
        "Preferred Dividends": 0.0,
        "Net Income Com": -22563000.0,
        "EPS": -0.07,
        "EPS Diluted": -0.07,
        "Weighted Average Shs Out": 302168000.0,
        "Weighted Average Shs Out (Dil)": 302168000.0,
        "Dividend per Share": 0.0,
        "Gross Margin": 0.112773113196,
        "EBITDA Margin": -0.148874620758,
        "EBIT Margin": -0.172142649953,
        "Profit Margin": -0.176885627602,
        "Free Cash Flow margin": -0.1338225264,
        "EBITDA": -18990000.0,
        "EBIT": -21958000.0,
        "Consolidated Income": -22563000.0,
        "Earnings Before Tax Margin": -0.171444922662,
        "Net Profit Margin": -0.176885627602
    },
    "2012": {
        "Revenue": 109371000.0,
        "Revenue Growth": 0.335584320429845,
        "Cost of Revenue": 103944000.0,
        "Gross Profit": 5427000.0,
        "R&D Expenses": 8237000.0,
        "SG&A Expense": 28927000.0,
        "Operating Expenses": 37164000.0,
        "Operating Income": -31737000.0,
        "Interest Expense": 857000.0,
        "Earnings before Tax": -18578000.0,
        "Income Tax Expense": 186000.0,
        "Net Income - Non-Controlling int": 0.0,
        "Net Income - Discontinued ops": 0.0,
        "Net Income": -18764000.0,
        "Preferred Dividends": 0.0,
        "Net Income Com": -18764000.0,
        "EPS": -0.07,
        "EPS Diluted": -0.07,
        "Weighted Average Shs Out": 266945000.0,
        "Weighted Average Shs Out (Dil)": 266945000.0,
        "Dividend per Share": 0.0,
        "Gross Margin": 0.0496201003922,
        "EBITDA Margin": -0.257508846038,
        "EBIT Margin": -0.290177469347,
        "Profit Margin": -0.171562845727,
        "Free Cash Flow margin": -0.196011739858,
        "EBITDA": -28164000.0,
        "EBIT": -31737000.0,
        "Consolidated Income": -18764000.0,
        "Earnings Before Tax Margin": -0.169862212104,
        "Net Profit Margin": -0.171562845727
    },
    "2011": {
        "Revenue": 81890000.0,
        "Revenue Growth": 0.330376579913572,
        "Cost of Revenue": 82427000.0,
        "Gross Profit": -537000.0,
        "R&D Expenses": 6986000.0,
        "SG&A Expense": 26203000.0,
        "Operating Expenses": 33189000.0,
        "Operating Income": -33726000.0,
        "Interest Expense": 873000.0,
        "Earnings before Tax": -38230000.0,
        "Income Tax Expense": 240000.0,
        "Net Income - Non-Controlling int": 0.0,
        "Net Income - Discontinued ops": 0.0,
        "Net Income": -38470000.0,
        "Preferred Dividends": 0.0,
        "Net Income Com": -38470000.0,
        "EPS": -32.0,
        "EPS Diluted": -32.0,
        "Weighted Average Shs Out": 1229919.0,
        "Weighted Average Shs Out (Dil)": 1229705.0,
        "Dividend per Share": 0.0,
        "Gross Margin": -0.0066,
        "EBITDA Margin": -0.41,
        "EBIT Margin": -0.4562,
        "Profit Margin": -0.47,
        "Free Cash Flow margin": -0.2802,
        "EBITDA": -33534000.0,
        "EBIT": -37357000.0,
        "Consolidated Income": -38470000.0,
        "Earnings Before Tax Margin": -0.4668,
        "Net Profit Margin": -0.4698
    },
    "2010": {
        "Revenue": 61554000.0,
        "Revenue Growth": 0.4006,
        "Cost of Revenue": 69999000.0,
        "Gross Profit": -8445000.0,
        "R&D Expenses": 6954000.0,
        "SG&A Expense": 28383000.0,
        "Operating Expenses": 35337000.0,
        "Operating Income": -43782000.0,
        "Interest Expense": 673000.0,
        "Earnings before Tax": -67300000.0,
        "Income Tax Expense": -59000.0,
        "Net Income - Non-Controlling int": 0.0,
        "Net Income - Discontinued ops": 0.0,
        "Net Income": -67241000.0,
        "Preferred Dividends": 0.0,
        "Net Income Com": -67241000.0,
        "EPS": -68.0,
        "EPS Diluted": -68.0,
        "Weighted Average Shs Out": 983299.0,
        "Weighted Average Shs Out (Dil)": 997895.0,
        "Dividend per Share": 0.0,
        "Gross Margin": -0.1372,
        "EBITDA Margin": -1.026,
        "EBIT Margin": -1.0824,
        "Profit Margin": -1.092,
        "Free Cash Flow margin": -0.5951,
        "EBITDA": -63131000.0,
        "EBIT": -66627000.0,
        "Consolidated Income": -67241000.0,
        "Earnings Before Tax Margin": -1.0933,
        "Net Profit Margin": -1.0924
    }
}