{
    "2018": {
        "Cash and cash equivalents": 2343000000.0,
        "Short-term investments": 10026000000.0,
        "Cash and short-term investments": 12369000000.0,
        "Receivables": 123000000.0,
        "Inventories": 0.0,
        "Total current assets": 16948000000.0,
        "Property, Plant & Equipment Net": 1735000000.0,
        "Goodwill and Intangible Assets": 4142000000.0,
        "Long-term investments": 411000000.0,
        "Tax assets": 245000000.0,
        "Total non-current assets": 8465000000.0,
        "Total assets": 25413000000.0,
        "Payables": 3067000000.0,
        "Short-term debt": 1694000000.0,
        "Total current liabilities": 10077000000.0,
        "Long-term debt": 4375000000.0,
        "Total debt": 6069000000.0,
        "Deferred revenue": 283000000.0,
        "Tax Liabilities": 0.0,
        "Deposit Liabilities": 0.0,
        "Total non-current liabilities": 5041000000.0,
        "Total liabilities": 15252000000.0,
        "Other comprehensive income": 0.0,
        "Retained earnings (deficit)": 15072000000.0,
        "Total shareholders equity": 10161000000.0,
        "Investments": 10437000000.0,
        "Net Debt": 3726000000.0,
        "Other Assets": 0.0,
        "Other Liabilities": 134000000.0
    },
    "2017": {
        "Cash and cash equivalents": 4042000000.0,
        "Short-term investments": 9557000000.0,
        "Cash and short-term investments": 13599000000.0,
        "Receivables": 0.0,
        "Inventories": 0.0,
        "Total current assets": 17402000000.0,
        "Property, Plant & Equipment Net": 1584000000.0,
        "Goodwill and Intangible Assets": 3507000000.0,
        "Long-term investments": 2745000000.0,
        "Tax assets": 547000000.0,
        "Total non-current assets": 9776000000.0,
        "Total assets": 27178000000.0,
        "Payables": 4069000000.0,
        "Short-term debt": 150000000.0,
        "Total current liabilities": 9406000000.0,
        "Long-term debt": 4770000000.0,
        "Total debt": 4920000000.0,
        "Deferred revenue": 378000000.0,
        "Tax Liabilities": 0.0,
        "Deposit Liabilities": 0.0,
        "Total non-current liabilities": 5337000000.0,
        "Total liabilities": 17336000000.0,
        "Other comprehensive income": 0.0,
        "Retained earnings (deficit)": 13670000000.0,
        "Total shareholders equity": 9842000000.0,
        "Investments": 12302000000.0,
        "Net Debt": 878000000.0,
        "Other Assets": 0.0,
        "Other Liabilities": 2593000000.0
    },
    "2016": {
        "Cash and cash equivalents": 3877000000.0,
        "Short-term investments": 7595000000.0,
        "Cash and short-term investments": 11472000000.0,
        "Receivables": 0.0,
        "Inventories": 0.0,
        "Total current assets": 16190000000.0,
        "Property, Plant & Equipment Net": 1505000000.0,
        "Goodwill and Intangible Assets": 3552000000.0,
        "Long-term investments": 2203000000.0,
        "Tax assets": 815000000.0,
        "Total non-current assets": 9206000000.0,
        "Total assets": 25396000000.0,
        "Payables": 2467000000.0,
        "Short-term debt": 300000000.0,
        "Total current liabilities": 7822000000.0,
        "Long-term debt": 3792000000.0,
        "Total debt": 4092000000.0,
        "Deferred revenue": 280000000.0,
        "Tax Liabilities": 0.0,
        "Deposit Liabilities": 0.0,
        "Total non-current liabilities": 4471000000.0,
        "Total liabilities": 14711000000.0,
        "Other comprehensive income": 0.0,
        "Retained earnings (deficit)": 11454000000.0,
        "Total shareholders equity": 10685000000.0,
        "Investments": 9798000000.0,
        "Net Debt": 215000000.0,
        "Other Assets": 0.0,
        "Other Liabilities": 2418000000.0
    },
    "2015": {
        "Cash and cash equivalents": 2571000000.0,
        "Short-term investments": 7267000000.0,
        "Cash and short-term investments": 9838000000.0,
        "Receivables": 0.0,
        "Inventories": 0.0,
        "Total current assets": 15711000000.0,
        "Property, Plant & Equipment Net": 1384000000.0,
        "Goodwill and Intangible Assets": 3622000000.0,
        "Long-term investments": 1843000000.0,
        "Tax assets": 701000000.0,
        "Total non-current assets": 8994000000.0,
        "Total assets": 24705000000.0,
        "Payables": 2212000000.0,
        "Short-term debt": 299000000.0,
        "Total current liabilities": 8152000000.0,
        "Long-term debt": 3821000000.0,
        "Total debt": 4120000000.0,
        "Deferred revenue": 364000000.0,
        "Tax Liabilities": 0.0,
        "Deposit Liabilities": 0.0,
        "Total non-current liabilities": 4501000000.0,
        "Total liabilities": 14359000000.0,
        "Other comprehensive income": 0.0,
        "Retained earnings (deficit)": 11017000000.0,
        "Total shareholders equity": 10346000000.0,
        "Investments": 9110000000.0,
        "Net Debt": 1549000000.0,
        "Other Assets": 0.0,
        "Other Liabilities": 1706000000.0
    },
    "2014": {
        "Cash and cash equivalents": 1935000000.0,
        "Short-term investments": 7598000000.0,
        "Cash and short-term investments": 9533000000.0,
        "Receivables": 0.0,
        "Inventories": 0.0,
        "Total current assets": 14712000000.0,
        "Property, Plant & Equipment Net": 1419000000.0,
        "Goodwill and Intangible Assets": 4283000000.0,
        "Long-term investments": 1949000000.0,
        "Tax assets": 734000000.0,
        "Total non-current assets": 8754000000.0,
        "Total assets": 23466000000.0,
        "Payables": 2185000000.0,
        "Short-term debt": 28000000.0,
        "Total current liabilities": 7355000000.0,
        "Long-term debt": 3825000000.0,
        "Total debt": 3853000000.0,
        "Deferred revenue": 361000000.0,
        "Tax Liabilities": 0.0,
        "Deposit Liabilities": 0.0,
        "Total non-current liabilities": 4749000000.0,
        "Total liabilities": 13820000000.0,
        "Other comprehensive income": 0.0,
        "Retained earnings (deficit)": 9916000000.0,
        "Total shareholders equity": 9646000000.0,
        "Investments": 9547000000.0,
        "Net Debt": 1918000000.0,
        "Other Assets": 0.0,
        "Other Liabilities": 1716000000.0
    },
    "2013": {
        "Cash and cash equivalents": 1138000000.0,
        "Short-term investments": 8090000000.0,
        "Cash and short-term investments": 9228000000.0,
        "Receivables": 777000000.0,
        "Inventories": 0.0,
        "Total current assets": 12300000000.0,
        "Property, Plant & Equipment Net": 1218000000.0,
        "Goodwill and Intangible Assets": 4426000000.0,
        "Long-term investments": 1710000000.0,
        "Tax assets": 688000000.0,
        "Total non-current assets": 8435000000.0,
        "Total assets": 20735000000.0,
        "Payables": 1821000000.0,
        "Short-term debt": 28000000.0,
        "Total current liabilities": 6323000000.0,
        "Long-term debt": 2600000000.0,
        "Total debt": 2628000000.0,
        "Deferred revenue": 206000000.0,
        "Tax Liabilities": 0.0,
        "Deposit Liabilities": 0.0,
        "Total non-current liabilities": 3503000000.0,
        "Total liabilities": 11419000000.0,
        "Other comprehensive income": 183000000.0,
        "Retained earnings (deficit)": 8942000000.0,
        "Total shareholders equity": 9316000000.0,
        "Investments": 9800000000.0,
        "Net Debt": 1490000000.0,
        "Other Assets": 0.0,
        "Other Liabilities": 1593000000.0
    },
    "2012": {
        "Cash and cash equivalents": 1306000000.0,
        "Short-term investments": 8001000000.0,
        "Cash and short-term investments": 9307000000.0,
        "Receivables": 523000000.0,
        "Inventories": 0.0,
        "Total current assets": 11710000000.0,
        "Property, Plant & Equipment Net": 1098000000.0,
        "Goodwill and Intangible Assets": 4371000000.0,
        "Long-term investments": 1846000000.0,
        "Tax assets": 756000000.0,
        "Total non-current assets": 8269000000.0,
        "Total assets": 19979000000.0,
        "Payables": 2042000000.0,
        "Short-term debt": 28000000.0,
        "Total current liabilities": 6375000000.0,
        "Long-term debt": 2611000000.0,
        "Total debt": 2639000000.0,
        "Deferred revenue": 230000000.0,
        "Tax Liabilities": 0.0,
        "Deposit Liabilities": 0.0,
        "Total non-current liabilities": 3688000000.0,
        "Total liabilities": 11132000000.0,
        "Other comprehensive income": 548000000.0,
        "Retained earnings (deficit)": 7881000000.0,
        "Total shareholders equity": 8847000000.0,
        "Investments": 9847000000.0,
        "Net Debt": 1333000000.0,
        "Other Assets": 0.0,
        "Other Liabilities": 1069000000.0
    },
    "2011": {
        "Cash and cash equivalents": 1377000000.0,
        "Short-term investments": 7743000000.0,
        "Cash and short-term investments": 9120000000.0,
        "Receivables": 572000000.0,
        "Inventories": 0.0,
        "Total current assets": 11181000000.0,
        "Property, Plant & Equipment Net": 912000000.0,
        "Goodwill and Intangible Assets": 3175000000.0,
        "Long-term investments": 1710000000.0,
        "Tax assets": 617000000.0,
        "Total non-current assets": 6527000000.0,
        "Total assets": 17708000000.0,
        "Payables": 1783000000.0,
        "Short-term debt": 28000000.0,
        "Total current liabilities": 6056000000.0,
        "Long-term debt": 1659000000.0,
        "Total debt": 1687000000.0,
        "Deferred revenue": 213000000.0,
        "Tax Liabilities": 0.0,
        "Deposit Liabilities": 0.0,
        "Total non-current liabilities": 2513000000.0,
        "Total liabilities": 9645000000.0,
        "Other comprehensive income": 903000000.0,
        "Retained earnings (deficit)": 6825000000.0,
        "Total shareholders equity": 8063000000.0,
        "Investments": 9453000000.0,
        "Net Debt": 310000000.0,
        "Other Assets": 0.0,
        "Other Liabilities": 1076000000.0
    },
    "2010": {
        "Cash and cash equivalents": 1673137000.0,
        "Short-term investments": 6872767000.0,
        "Cash and short-term investments": 8545904000.0,
        "Receivables": 379406000.0,
        "Inventories": 0.0,
        "Total current assets": 10137699000.0,
        "Property, Plant & Equipment Net": 815337000.0,
        "Goodwill and Intangible Assets": 2583199000.0,
        "Long-term investments": 1499672000.0,
        "Tax assets": 554076000.0,
        "Total non-current assets": 5965554000.0,
        "Total assets": 16103253000.0,
        "Payables": 1624832000.0,
        "Short-term debt": 27600000.0,
        "Total current liabilities": 5744626000.0,
        "Long-term debt": 1668849000.0,
        "Total debt": 1696449000.0,
        "Deferred revenue": 185410000.0,
        "Tax Liabilities": 0.0,
        "Deposit Liabilities": 0.0,
        "Total non-current liabilities": 2330391000.0,
        "Total liabilities": 9179197000.0,
        "Other comprehensive income": 1242764000.0,
        "Retained earnings (deficit)": 5529001000.0,
        "Total shareholders equity": 6924056000.0,
        "Investments": 8372439000.0,
        "Net Debt": 23312000.0,
        "Other Assets": 0.0,
        "Other Liabilities": 1104180000.0
    },
    "2009": {
        "Cash and cash equivalents": 1613588000.0,
        "Short-term investments": 6190062000.0,
        "Cash and short-term investments": 7803650000.0,
        "Receivables": 823620000.0,
        "Inventories": 0.0,
        "Total current assets": 9252816000.0,
        "Property, Plant & Equipment Net": 679142000.0,
        "Goodwill and Intangible Assets": 1992924000.0,
        "Long-term investments": 1307088000.0,
        "Tax assets": 0.0,
        "Total non-current assets": 4900678000.0,
        "Total assets": 14153494000.0,
        "Payables": 5849758000.0,
        "Short-term debt": 374464000.0,
        "Total current liabilities": 5259992000.0,
        "Long-term debt": 1678166000.0,
        "Total debt": 2052630000.0,
        "Deferred revenue": 228817000.0,
        "Tax Liabilities": 0.0,
        "Deposit Liabilities": 0.0,
        "Total non-current liabilities": 3117499000.0,
        "Total liabilities": 8377491000.0,
        "Other comprehensive income": 42135000.0,
        "Retained earnings (deficit)": 4429611000.0,
        "Total shareholders equity": 5776003000.0,
        "Investments": 7497150000.0,
        "Net Debt": -5751020000.0,
        "Other Assets": 625546000.0,
        "Other Liabilities": -964230000.0
    }
}