{
    "2018": {
        "Revenue": 2189100000.0,
        "Revenue Growth": 0.109359955404652,
        "Cost of Revenue": 1608300000.0,
        "Gross Profit": 580800000.0,
        "R&D Expenses": 55900000.0,
        "SG&A Expense": 146000000.0,
        "Operating Expenses": 201900000.0,
        "Operating Income": 371200000.0,
        "Interest Expense": 37700000.0,
        "Earnings before Tax": 222900000.0,
        "Income Tax Expense": 62500000.0,
        "Net Income - Non-Controlling int": 0.0,
        "Net Income - Discontinued ops": 0.0,
        "Net Income": 276600000.0,
        "Preferred Dividends": 0.0,
        "Net Income Com": 276600000.0,
        "EPS": 3.11,
        "EPS Diluted": 3.11,
        "Weighted Average Shs Out": 87900000.0,
        "Weighted Average Shs Out (Dil)": 89000000.0,
        "Dividend per Share": 0.543820224719,
        "Gross Margin": 0.265314512813,
        "EBITDA Margin": 0.226531451281,
        "EBIT Margin": 0.169567402129,
        "Profit Margin": 0.126353295875,
        "Free Cash Flow margin": 0.108400712622,
        "EBITDA": 495900000.0,
        "EBIT": 371200000.0,
        "Consolidated Income": 276600000.0,
        "Earnings Before Tax Margin": 0.101822666849,
        "Net Profit Margin": 0.126353295875
    },
    "2017": {
        "Revenue": 1973300000.0,
        "Revenue Growth": -0.0154667464950357,
        "Cost of Revenue": 1421500000.0,
        "Gross Profit": 551800000.0,
        "R&D Expenses": 49400000.0,
        "SG&A Expense": 151800000.0,
        "Operating Expenses": 201200000.0,
        "Operating Income": 350600000.0,
        "Interest Expense": 27400000.0,
        "Earnings before Tax": 155500000.0,
        "Income Tax Expense": 42500000.0,
        "Net Income - Non-Controlling int": 0.0,
        "Net Income - Discontinued ops": 0.0,
        "Net Income": 284000000.0,
        "Preferred Dividends": 0.0,
        "Net Income Com": 284000000.0,
        "EPS": 3.09,
        "EPS Diluted": 3.09,
        "Weighted Average Shs Out": 90600000.0,
        "Weighted Average Shs Out (Dil)": 91900000.0,
        "Dividend per Share": 0.463547334059,
        "Gross Margin": 0.279633101911,
        "EBITDA Margin": 0.23098363148,
        "EBIT Margin": 0.177671920134,
        "Profit Margin": 0.143921350023,
        "Free Cash Flow margin": 0.0763188567374,
        "EBITDA": 455800000.0,
        "EBIT": 350600000.0,
        "Consolidated Income": 284000000.0,
        "Earnings Before Tax Margin": 0.0788020067907,
        "Net Profit Margin": 0.143921350023
    },
    "2016": {
        "Revenue": 2004300000.0,
        "Revenue Growth": 0.0768858800773694,
        "Cost of Revenue": 1439700000.0,
        "Gross Profit": 564600000.0,
        "R&D Expenses": 46900000.0,
        "SG&A Expense": 157600000.0,
        "Operating Expenses": 204500000.0,
        "Operating Income": 360100000.0,
        "Interest Expense": 22100000.0,
        "Earnings before Tax": 149100000.0,
        "Income Tax Expense": 90300000.0,
        "Net Income - Non-Controlling int": 0.0,
        "Net Income - Discontinued ops": 0.0,
        "Net Income": 249800000.0,
        "Preferred Dividends": 0.0,
        "Net Income Com": 249800000.0,
        "EPS": 2.65,
        "EPS Diluted": 2.65,
        "Weighted Average Shs Out": 92800000.0,
        "Weighted Average Shs Out (Dil)": 94200000.0,
        "Dividend per Share": 0.422505307856,
        "Gross Margin": 0.281694357132,
        "EBITDA Margin": 0.227061817093,
        "EBIT Margin": 0.179663722996,
        "Profit Margin": 0.124632041112,
        "Free Cash Flow margin": 0.0366711570124,
        "EBITDA": 455100000.0,
        "EBIT": 360100000.0,
        "Consolidated Income": 249800000.0,
        "Earnings Before Tax Margin": 0.0743900613681,
        "Net Profit Margin": 0.124632041112
    },
    "2015": {
        "Revenue": 1861200000.0,
        "Revenue Growth": 0.00307194826192401,
        "Cost of Revenue": 1328400000.0,
        "Gross Profit": 532800000.0,
        "R&D Expenses": 44300000.0,
        "SG&A Expense": 156100000.0,
        "Operating Expenses": 200400000.0,
        "Operating Income": 332400000.0,
        "Interest Expense": 14200000.0,
        "Earnings before Tax": 164300000.0,
        "Income Tax Expense": 83000000.0,
        "Net Income - Non-Controlling int": 0.0,
        "Net Income - Discontinued ops": 0.0,
        "Net Income": 237200000.0,
        "Preferred Dividends": 0.0,
        "Net Income Com": 237200000.0,
        "EPS": 2.48,
        "EPS Diluted": 2.44,
        "Weighted Average Shs Out": 95800000.0,
        "Weighted Average Shs Out (Dil)": 97200000.0,
        "Dividend per Share": 0.394032921811,
        "Gross Margin": 0.286266924565,
        "EBITDA Margin": 0.220234257468,
        "EBIT Margin": 0.17859445519,
        "Profit Margin": 0.12744465936,
        "Free Cash Flow margin": -0.00231033741672,
        "EBITDA": 409900000.0,
        "EBIT": 332400000.0,
        "Consolidated Income": 237200000.0,
        "Earnings Before Tax Margin": 0.0882763808296,
        "Net Profit Margin": 0.12744465936
    },
    "2014": {
        "Revenue": 1855500000.0,
        "Revenue Growth": 0.105648909545942,
        "Cost of Revenue": 1346700000.0,
        "Gross Profit": 508800000.0,
        "R&D Expenses": 47900000.0,
        "SG&A Expense": 149100000.0,
        "Operating Expenses": 197000000.0,
        "Operating Income": 305800000.0,
        "Interest Expense": 8000000.0,
        "Earnings before Tax": 163800000.0,
        "Income Tax Expense": 89300000.0,
        "Net Income - Non-Controlling int": 0.0,
        "Net Income - Discontinued ops": 0.0,
        "Net Income": 209400000.0,
        "Preferred Dividends": 0.0,
        "Net Income Com": 209400000.0,
        "EPS": 2.16,
        "EPS Diluted": 2.12,
        "Weighted Average Shs Out": 96800000.0,
        "Weighted Average Shs Out (Dil)": 98700000.0,
        "Dividend per Share": 0.0,
        "Gross Margin": 0.274211802749,
        "EBITDA Margin": 0.204042037187,
        "EBIT Margin": 0.164807329561,
        "Profit Margin": 0.112853678254,
        "Free Cash Flow margin": 0.0312045270816,
        "EBITDA": 378600000.0,
        "EBIT": 305800000.0,
        "Consolidated Income": 209400000.0,
        "Earnings Before Tax Margin": 0.0882780921584,
        "Net Profit Margin": 0.112853678254
    },
    "2013": {
        "Revenue": 1678200000.0,
        "Revenue Growth": 0.0633633253073121,
        "Cost of Revenue": 1224200000.0,
        "Gross Profit": 454000000.0,
        "R&D Expenses": 41700000.0,
        "SG&A Expense": 141400000.0,
        "Operating Expenses": 183100000.0,
        "Operating Income": 270900000.0,
        "Interest Expense": 7300000.0,
        "Earnings before Tax": 149800000.0,
        "Income Tax Expense": 76000000.0,
        "Net Income - Non-Controlling int": 0.0,
        "Net Income - Discontinued ops": 0.0,
        "Net Income": 187900000.0,
        "Preferred Dividends": 0.0,
        "Net Income Com": 187900000.0,
        "EPS": 1.88,
        "EPS Diluted": 1.84,
        "Weighted Average Shs Out": 100000000.0,
        "Weighted Average Shs Out (Dil)": 102100000.0,
        "Dividend per Share": 0.0,
        "Gross Margin": 0.270527946609,
        "EBITDA Margin": 0.198009772375,
        "EBIT Margin": 0.161422953164,
        "Profit Margin": 0.11196520081,
        "Free Cash Flow margin": 0.0464783696818,
        "EBITDA": 332300000.0,
        "EBIT": 270900000.0,
        "Consolidated Income": 187900000.0,
        "Earnings Before Tax Margin": 0.0892623048504,
        "Net Profit Margin": 0.11196520081
    },
    "2012": {
        "Revenue": 1578200000.0,
        "Revenue Growth": 0.133438667049698,
        "Cost of Revenue": 1171500000.0,
        "Gross Profit": 406700000.0,
        "R&D Expenses": 36700000.0,
        "SG&A Expense": 130700000.0,
        "Operating Expenses": 167400000.0,
        "Operating Income": 248800000.0,
        "Interest Expense": 10000000.0,
        "Earnings before Tax": 237700000.0,
        "Income Tax Expense": 74100000.0,
        "Net Income - Non-Controlling int": 0.0,
        "Net Income - Discontinued ops": 0.0,
        "Net Income": 164300000.0,
        "Preferred Dividends": 0.0,
        "Net Income Com": 164300000.0,
        "EPS": 1.64,
        "EPS Diluted": 1.61,
        "Weighted Average Shs Out": 100200000.0,
        "Weighted Average Shs Out (Dil)": 102000000.0,
        "Dividend per Share": 0.0,
        "Gross Margin": 0.257698644025,
        "EBITDA Margin": 0.195856038525,
        "EBIT Margin": 0.157647953365,
        "Profit Margin": 0.10410594348,
        "Free Cash Flow margin": -0.0198327208212,
        "EBITDA": 309100000.0,
        "EBIT": 248800000.0,
        "Consolidated Income": 164300000.0,
        "Earnings Before Tax Margin": 0.150614624255,
        "Net Profit Margin": 0.10410594348
    },
    "2011": {
        "Revenue": 1392400000.0,
        "Revenue Growth": 0.186434901158828,
        "Cost of Revenue": 1050300000.0,
        "Gross Profit": 342100000.0,
        "R&D Expenses": 32600000.0,
        "SG&A Expense": 120500000.0,
        "Operating Expenses": 153100000.0,
        "Operating Income": 192000000.0,
        "Interest Expense": 11600000.0,
        "Earnings before Tax": 175500000.0,
        "Income Tax Expense": 41600000.0,
        "Net Income - Non-Controlling int": 0.0,
        "Net Income - Discontinued ops": 0.0,
        "Net Income": 135500000.0,
        "Preferred Dividends": 0.0,
        "Net Income Com": 135500000.0,
        "EPS": 1.37,
        "EPS Diluted": 1.35,
        "Weighted Average Shs Out": 98800000.0,
        "Weighted Average Shs Out (Dil)": 100700000.0,
        "Dividend per Share": 0.0,
        "Gross Margin": 0.245690893421,
        "EBITDA Margin": 0.182706118931,
        "EBIT Margin": 0.137891410514,
        "Profit Margin": 0.0973139902327,
        "Free Cash Flow margin": 0.00897730537202,
        "EBITDA": 254400000.0,
        "EBIT": 192000000.0,
        "Consolidated Income": 135500000.0,
        "Earnings Before Tax Margin": 0.126041367423,
        "Net Profit Margin": 0.0973139902327
    },
    "2010": {
        "Revenue": 1173600000.0,
        "Revenue Growth": 0.0589190652350447,
        "Cost of Revenue": 891000000.0,
        "Gross Profit": 282600000.0,
        "R&D Expenses": 30800000.0,
        "SG&A Expense": 118500000.0,
        "Operating Expenses": 149300000.0,
        "Operating Income": 129800000.0,
        "Interest Expense": 23200000.0,
        "Earnings before Tax": 99800000.0,
        "Income Tax Expense": 22900000.0,
        "Net Income - Non-Controlling int": 0.0,
        "Net Income - Discontinued ops": 0.0,
        "Net Income": 77400000.0,
        "Preferred Dividends": 0.0,
        "Net Income Com": 77400000.0,
        "EPS": 0.79,
        "EPS Diluted": 0.77,
        "Weighted Average Shs Out": 97600000.0,
        "Weighted Average Shs Out (Dil)": 99900000.0,
        "Dividend per Share": 0.0,
        "Gross Margin": 0.240797546012,
        "EBITDA Margin": 0.164706884799,
        "EBIT Margin": 0.110599863667,
        "Profit Margin": 0.0659509202454,
        "Free Cash Flow margin": 0.0662065439673,
        "EBITDA": 193300000.0,
        "EBIT": 129800000.0,
        "Consolidated Income": 77400000.0,
        "Earnings Before Tax Margin": 0.0850374914792,
        "Net Profit Margin": 0.0659509202454
    },
    "2009": {
        "Revenue": 1108300000.0,
        "Revenue Growth": -0.1635,
        "Cost of Revenue": 859800000.0,
        "Gross Profit": 248500000.0,
        "R&D Expenses": 30100000.0,
        "SG&A Expense": 107200000.0,
        "Operating Expenses": 137300000.0,
        "Operating Income": 111200000.0,
        "Interest Expense": 26100000.0,
        "Earnings before Tax": 78300000.0,
        "Income Tax Expense": 22000000.0,
        "Net Income - Non-Controlling int": 0.0,
        "Net Income - Discontinued ops": 0.0,
        "Net Income": 56300000.0,
        "Preferred Dividends": 0.0,
        "Net Income Com": 56300000.0,
        "EPS": 0.58,
        "EPS Diluted": 0.57,
        "Weighted Average Shs Out": 96650266.0,
        "Weighted Average Shs Out (Dil)": 96900000.0,
        "Dividend per Share": 0.0,
        "Gross Margin": 0.2242,
        "EBITDA Margin": 0.136,
        "EBIT Margin": 0.0942,
        "Profit Margin": 0.051,
        "Free Cash Flow margin": 0.0671,
        "EBITDA": 151000000.0,
        "EBIT": 104400000.0,
        "Consolidated Income": 56300000.0,
        "Earnings Before Tax Margin": 0.0706,
        "Net Profit Margin": 0.0508
    }
}