{
    "2019": {
        "Cash and cash equivalents": 517309.0,
        "Short-term investments": 0.0,
        "Cash and short-term investments": 517309.0,
        "Receivables": 16494234.0,
        "Inventories": 44232340.0,
        "Total current assets": 66995265.0,
        "Property, Plant & Equipment Net": 724597.0,
        "Goodwill and Intangible Assets": 6261170.0,
        "Long-term investments": 0.0,
        "Tax assets": 9552385.0,
        "Total non-current assets": 17985301.0,
        "Total assets": 84980566.0,
        "Payables": 11375965.0,
        "Short-term debt": 87678.0,
        "Total current liabilities": 18046580.0,
        "Long-term debt": 211580.0,
        "Total debt": 299258.0,
        "Deferred revenue": 0.0,
        "Tax Liabilities": 41000.0,
        "Deposit Liabilities": 0.0,
        "Total non-current liabilities": 769517.0,
        "Total liabilities": 72381430.0,
        "Other comprehensive income": 157342730.0,
        "Retained earnings (deficit)": -144227656.0,
        "Total shareholders equity": 12599136.0,
        "Investments": 0.0,
        "Net Debt": -218051.0,
        "Other Assets": 0.0,
        "Other Liabilities": 53565333.0
    },
    "2018": {
        "Cash and cash equivalents": 376987.0,
        "Short-term investments": 0.0,
        "Cash and short-term investments": 376987.0,
        "Receivables": 13083487.0,
        "Inventories": 34555553.0,
        "Total current assets": 51740786.0,
        "Property, Plant & Equipment Net": 839409.0,
        "Goodwill and Intangible Assets": 6465171.0,
        "Long-term investments": 0.0,
        "Tax assets": 398000.0,
        "Total non-current assets": 8592574.0,
        "Total assets": 60333360.0,
        "Payables": 7674858.0,
        "Short-term debt": 176148.0,
        "Total current liabilities": 13133917.0,
        "Long-term debt": 211580.0,
        "Total debt": 387728.0,
        "Deferred revenue": 0.0,
        "Tax Liabilities": 6000.0,
        "Deposit Liabilities": 0.0,
        "Total non-current liabilities": 703842.0,
        "Total liabilities": 55912292.0,
        "Other comprehensive income": 154731044.0,
        "Retained earnings (deficit)": -149891272.0,
        "Total shareholders equity": 4421068.0,
        "Investments": 0.0,
        "Net Debt": 10741.0,
        "Other Assets": 0.0,
        "Other Liabilities": 42074533.0
    },
    "2017": {
        "Cash and cash equivalents": 611048.0,
        "Short-term investments": 0.0,
        "Cash and short-term investments": 611048.0,
        "Receivables": 11460432.0,
        "Inventories": 29801080.0,
        "Total current assets": 45547483.0,
        "Property, Plant & Equipment Net": 909780.0,
        "Goodwill and Intangible Assets": 6883556.0,
        "Long-term investments": 0.0,
        "Tax assets": 490000.0,
        "Total non-current assets": 8794661.0,
        "Total assets": 54342144.0,
        "Payables": 7549942.0,
        "Short-term debt": 2158318.0,
        "Total current liabilities": 14376968.0,
        "Long-term debt": 211580.0,
        "Total debt": 2369898.0,
        "Deferred revenue": 0.0,
        "Tax Liabilities": 18000.0,
        "Deposit Liabilities": 0.0,
        "Total non-current liabilities": 770346.0,
        "Total liabilities": 52355567.0,
        "Other comprehensive income": 150889613.0,
        "Retained earnings (deficit)": -148223822.0,
        "Total shareholders equity": 1986577.0,
        "Investments": 0.0,
        "Net Debt": 1758850.0,
        "Other Assets": 0.0,
        "Other Liabilities": 37208253.0
    },
    "2016": {
        "Cash and cash equivalents": 1430532.0,
        "Short-term investments": 0.0,
        "Cash and short-term investments": 1430532.0,
        "Receivables": 10410571.0,
        "Inventories": 27233322.0,
        "Total current assets": 40689501.0,
        "Property, Plant & Equipment Net": 876255.0,
        "Goodwill and Intangible Assets": 7544528.0,
        "Long-term investments": 0.0,
        "Tax assets": 18000.0,
        "Total non-current assets": 9584912.0,
        "Total assets": 50274413.0,
        "Payables": 5652260.0,
        "Short-term debt": 0.0,
        "Total current liabilities": 11342502.0,
        "Long-term debt": 211580.0,
        "Total debt": 211580.0,
        "Deferred revenue": 0.0,
        "Tax Liabilities": 0.0,
        "Deposit Liabilities": 0.0,
        "Total non-current liabilities": 1415580.0,
        "Total liabilities": 29874867.0,
        "Other comprehensive income": 166866671.0,
        "Retained earnings (deficit)": -145878079.0,
        "Total shareholders equity": 20399546.0,
        "Investments": 0.0,
        "Net Debt": -1218952.0,
        "Other Assets": 0.0,
        "Other Liabilities": 17116785.0
    },
    "2015": {
        "Cash and cash equivalents": 1191603.0,
        "Short-term investments": 0.0,
        "Cash and short-term investments": 1191603.0,
        "Receivables": 10550990.0,
        "Inventories": 21068241.0,
        "Total current assets": 34479390.0,
        "Property, Plant & Equipment Net": 665373.0,
        "Goodwill and Intangible Assets": 8179453.0,
        "Long-term investments": 0.0,
        "Tax assets": 37000.0,
        "Total non-current assets": 9559550.0,
        "Total assets": 44038940.0,
        "Payables": 5753617.0,
        "Short-term debt": 31466.0,
        "Total current liabilities": 8819101.0,
        "Long-term debt": 211580.0,
        "Total debt": 243046.0,
        "Deferred revenue": 0.0,
        "Tax Liabilities": 0.0,
        "Deposit Liabilities": 0.0,
        "Total non-current liabilities": 1581732.0,
        "Total liabilities": 25487806.0,
        "Other comprehensive income": 162626893.0,
        "Retained earnings (deficit)": -143361711.0,
        "Total shareholders equity": 18551134.0,
        "Investments": 0.0,
        "Net Debt": -948557.0,
        "Other Assets": 0.0,
        "Other Liabilities": 15086973.0
    },
    "2014": {
        "Cash and cash equivalents": 908501.0,
        "Short-term investments": 0.0,
        "Cash and short-term investments": 908501.0,
        "Receivables": 8858146.0,
        "Inventories": 14650029.0,
        "Total current assets": 26581241.0,
        "Property, Plant & Equipment Net": 568395.0,
        "Goodwill and Intangible Assets": 8675114.0,
        "Long-term investments": 0.0,
        "Tax assets": 473330.0,
        "Total non-current assets": 9940269.0,
        "Total assets": 36521510.0,
        "Payables": 4483764.0,
        "Short-term debt": 14693.0,
        "Total current liabilities": 7513398.0,
        "Long-term debt": 211580.0,
        "Total debt": 226273.0,
        "Deferred revenue": 0.0,
        "Tax Liabilities": 0.0,
        "Deposit Liabilities": 0.0,
        "Total non-current liabilities": 1729884.0,
        "Total liabilities": 18804019.0,
        "Other comprehensive income": 157485965.0,
        "Retained earnings (deficit)": -139561969.0,
        "Total shareholders equity": 17717491.0,
        "Investments": 0.0,
        "Net Debt": -682228.0,
        "Other Assets": 0.0,
        "Other Liabilities": 9560737.0
    },
    "2013": {
        "Cash and cash equivalents": 439323.0,
        "Short-term investments": 0.0,
        "Cash and short-term investments": 439323.0,
        "Receivables": 7025358.0,
        "Inventories": 13731962.0,
        "Total current assets": 22483703.0,
        "Property, Plant & Equipment Net": 516641.0,
        "Goodwill and Intangible Assets": 9296199.0,
        "Long-term investments": 0.0,
        "Tax assets": 0.0,
        "Total non-current assets": 10633392.0,
        "Total assets": 33117095.0,
        "Payables": 5301524.0,
        "Short-term debt": 69761.0,
        "Total current liabilities": 8536131.0,
        "Long-term debt": 211580.0,
        "Total debt": 281341.0,
        "Deferred revenue": 0.0,
        "Tax Liabilities": 0.0,
        "Deposit Liabilities": 0.0,
        "Total non-current liabilities": 1878036.0,
        "Total liabilities": 21489527.0,
        "Other comprehensive income": 142728555.0,
        "Retained earnings (deficit)": -130270623.0,
        "Total shareholders equity": 11627568.0,
        "Investments": 0.0,
        "Net Debt": -157982.0,
        "Other Assets": 0.0,
        "Other Liabilities": 11075360.0
    },
    "2012": {
        "Cash and cash equivalents": 484362.0,
        "Short-term investments": 0.0,
        "Cash and short-term investments": 484362.0,
        "Receivables": 6268432.0,
        "Inventories": 10732698.0,
        "Total current assets": 18392463.0,
        "Property, Plant & Equipment Net": 620840.0,
        "Goodwill and Intangible Assets": 11545346.0,
        "Long-term investments": 0.0,
        "Tax assets": 0.0,
        "Total non-current assets": 12962314.0,
        "Total assets": 31354777.0,
        "Payables": 4771140.0,
        "Short-term debt": 0.0,
        "Total current liabilities": 6798028.0,
        "Long-term debt": 4061411.0,
        "Total debt": 4061411.0,
        "Deferred revenue": 0.0,
        "Tax Liabilities": 0.0,
        "Deposit Liabilities": 0.0,
        "Total non-current liabilities": 5876019.0,
        "Total liabilities": 14030910.0,
        "Other comprehensive income": 142121611.0,
        "Retained earnings (deficit)": -124076608.0,
        "Total shareholders equity": 17323867.0,
        "Investments": 0.0,
        "Net Debt": 3577049.0,
        "Other Assets": 0.0,
        "Other Liabilities": 1356863.0
    },
    "2011": {
        "Cash and cash equivalents": 1515379.0,
        "Short-term investments": 0.0,
        "Cash and short-term investments": 1515379.0,
        "Receivables": 5852855.0,
        "Inventories": 9869080.0,
        "Total current assets": 13327454.0,
        "Property, Plant & Equipment Net": 509554.0,
        "Goodwill and Intangible Assets": 12125345.0,
        "Long-term investments": 155573.0,
        "Tax assets": 0.0,
        "Total non-current assets": 7873244.0,
        "Total assets": 31105646.0,
        "Payables": 5179310.0,
        "Short-term debt": 426175.0,
        "Total current liabilities": 6339036.0,
        "Long-term debt": 5910484.0,
        "Total debt": 6336659.0,
        "Deferred revenue": 0.0,
        "Tax Liabilities": 0.0,
        "Deposit Liabilities": 0.0,
        "Total non-current liabilities": 7873244.0,
        "Total liabilities": 14212280.0,
        "Other comprehensive income": -1633502.0,
        "Retained earnings (deficit)": -118413246.0,
        "Total shareholders equity": 16493393.0,
        "Investments": 155573.0,
        "Net Debt": 4821280.0,
        "Other Assets": 540878.0,
        "Other Liabilities": 733551.0
    },
    "2010": {
        "Cash and cash equivalents": 1975107.0,
        "Short-term investments": 0.0,
        "Cash and short-term investments": 1975107.0,
        "Receivables": 5396211.0,
        "Inventories": 9243801.0,
        "Total current assets": 14008601.0,
        "Property, Plant & Equipment Net": 482025.0,
        "Goodwill and Intangible Assets": 12663476.0,
        "Long-term investments": 0.0,
        "Tax assets": 0.0,
        "Total non-current assets": 2544946.0,
        "Total assets": 30889787.0,
        "Payables": 4502733.0,
        "Short-term debt": 425435.0,
        "Total current liabilities": 5586102.0,
        "Long-term debt": 434034.0,
        "Total debt": 859469.0,
        "Deferred revenue": 0.0,
        "Tax Liabilities": 0.0,
        "Deposit Liabilities": 0.0,
        "Total non-current liabilities": 2544946.0,
        "Total liabilities": 8131048.0,
        "Other comprehensive income": -1768531.0,
        "Retained earnings (deficit)": -112105964.0,
        "Total shareholders equity": 22671505.0,
        "Investments": 0.0,
        "Net Debt": -1115638.0,
        "Other Assets": 266067.0,
        "Other Liabilities": 657934.0
    }
}