{
    "2018": {
        "Depreciation & Amortization": 0.0,
        "Stock-based compensation": 0.0,
        "Operating Cash Flow": 0.0,
        "Capital Expenditure": 0.0,
        "Acquisitions and disposals": -0.0,
        "Investment purchases and sales": 0.0,
        "Investing Cash flow": 16617000.0,
        "Issuance (repayment) of debt": -0.0,
        "Issuance (buybacks) of shares": -16617000.0,
        "Dividend payments": -0.0,
        "Financing Cash Flow": 0.0,
        "Effect of forex changes on cash": 0.0,
        "Net cash flow / Change in cash": 16617000.0,
        "Free Cash Flow": 0.0,
        "Net Cash/Marketcap": 0.0
    },
    "2017": {
        "Depreciation & Amortization": 11080000.0,
        "Stock-based compensation": 1015000.0,
        "Operating Cash Flow": 15528000.0,
        "Capital Expenditure": 7185000.0,
        "Acquisitions and disposals": -0.0,
        "Investment purchases and sales": 0.0,
        "Investing Cash flow": -6835000.0,
        "Issuance (repayment) of debt": -0.0,
        "Issuance (buybacks) of shares": -433000.0,
        "Dividend payments": -0.0,
        "Financing Cash Flow": -8784000.0,
        "Effect of forex changes on cash": 508000.0,
        "Net cash flow / Change in cash": 1456000.0,
        "Free Cash Flow": 8343000.0,
        "Net Cash/Marketcap": 0.0
    },
    "2016": {
        "Depreciation & Amortization": 12250000.0,
        "Stock-based compensation": 1722000.0,
        "Operating Cash Flow": 10937000.0,
        "Capital Expenditure": 3797000.0,
        "Acquisitions and disposals": -825000.0,
        "Investment purchases and sales": 0.0,
        "Investing Cash flow": -4582000.0,
        "Issuance (repayment) of debt": -0.0,
        "Issuance (buybacks) of shares": -639000.0,
        "Dividend payments": -0.0,
        "Financing Cash Flow": -8844000.0,
        "Effect of forex changes on cash": 902000.0,
        "Net cash flow / Change in cash": 1039000.0,
        "Free Cash Flow": 7140000.0,
        "Net Cash/Marketcap": 0.0
    },
    "2015": {
        "Depreciation & Amortization": 13261000.0,
        "Stock-based compensation": 1469000.0,
        "Operating Cash Flow": -4636000.0,
        "Capital Expenditure": 7722000.0,
        "Acquisitions and disposals": -18258000.0,
        "Investment purchases and sales": 0.0,
        "Investing Cash flow": -24998000.0,
        "Issuance (repayment) of debt": -373000.0,
        "Issuance (buybacks) of shares": -2445000.0,
        "Dividend payments": -0.0,
        "Financing Cash Flow": 26519000.0,
        "Effect of forex changes on cash": 435000.0,
        "Net cash flow / Change in cash": 2626000.0,
        "Free Cash Flow": -12358000.0,
        "Net Cash/Marketcap": 0.0
    },
    "2014": {
        "Depreciation & Amortization": 10379000.0,
        "Stock-based compensation": 1625000.0,
        "Operating Cash Flow": 4380000.0,
        "Capital Expenditure": 11661000.0,
        "Acquisitions and disposals": -3419000.0,
        "Investment purchases and sales": 0.0,
        "Investing Cash flow": -13300000.0,
        "Issuance (repayment) of debt": -183000.0,
        "Issuance (buybacks) of shares": -5188000.0,
        "Dividend payments": -0.0,
        "Financing Cash Flow": 3416000.0,
        "Effect of forex changes on cash": -179000.0,
        "Net cash flow / Change in cash": 5306000.0,
        "Free Cash Flow": -7281000.0,
        "Net Cash/Marketcap": 0.0
    },
    "2013": {
        "Depreciation & Amortization": 12527000.0,
        "Stock-based compensation": 1607000.0,
        "Operating Cash Flow": 6242000.0,
        "Capital Expenditure": 8843000.0,
        "Acquisitions and disposals": -2097000.0,
        "Investment purchases and sales": 0.0,
        "Investing Cash flow": 3534000.0,
        "Issuance (repayment) of debt": -0.0,
        "Issuance (buybacks) of shares": -10892000.0,
        "Dividend payments": -0.0,
        "Financing Cash Flow": 1213000.0,
        "Effect of forex changes on cash": -98000.0,
        "Net cash flow / Change in cash": 10989000.0,
        "Free Cash Flow": -2601000.0,
        "Net Cash/Marketcap": 0.0
    },
    "2012": {
        "Depreciation & Amortization": 12957000.0,
        "Stock-based compensation": 1275000.0,
        "Operating Cash Flow": 2911000.0,
        "Capital Expenditure": 7305000.0,
        "Acquisitions and disposals": -0.0,
        "Investment purchases and sales": 0.0,
        "Investing Cash flow": -2761000.0,
        "Issuance (repayment) of debt": -0.0,
        "Issuance (buybacks) of shares": -9080000.0,
        "Dividend payments": -0.0,
        "Financing Cash Flow": 7000.0,
        "Effect of forex changes on cash": -693000.0,
        "Net cash flow / Change in cash": 9183000.0,
        "Free Cash Flow": -4394000.0,
        "Net Cash/Marketcap": 0.0
    },
    "2011": {
        "Depreciation & Amortization": 15750000.0,
        "Stock-based compensation": 1602000.0,
        "Operating Cash Flow": -1268000.0,
        "Capital Expenditure": 8958000.0,
        "Acquisitions and disposals": -0.0,
        "Investment purchases and sales": 0.0,
        "Investing Cash flow": -8298000.0,
        "Issuance (repayment) of debt": -0.0,
        "Issuance (buybacks) of shares": -9596000.0,
        "Dividend payments": -0.0,
        "Financing Cash Flow": 149000.0,
        "Effect of forex changes on cash": 396000.0,
        "Net cash flow / Change in cash": -9021000.0,
        "Free Cash Flow": -10226000.0,
        "Net Cash/Marketcap": 0.0
    },
    "2010": {
        "Depreciation & Amortization": NaN,
        "Stock-based compensation": NaN,
        "Operating Cash Flow": 14717000.0,
        "Capital Expenditure": -16942000.0,
        "Acquisitions and disposals": NaN,
        "Investment purchases and sales": NaN,
        "Investing Cash flow": -16061000.0,
        "Issuance (repayment) of debt": -147000.0,
        "Issuance (buybacks) of shares": 417000.0,
        "Dividend payments": 0.0,
        "Financing Cash Flow": 270000.0,
        "Effect of forex changes on cash": NaN,
        "Net cash flow / Change in cash": NaN,
        "Free Cash Flow": NaN,
        "Net Cash/Marketcap": NaN
    },
    "2009": {
        "Depreciation & Amortization": NaN,
        "Stock-based compensation": NaN,
        "Operating Cash Flow": 15654000.0,
        "Capital Expenditure": -14683000.0,
        "Acquisitions and disposals": NaN,
        "Investment purchases and sales": NaN,
        "Investing Cash flow": 411000.0,
        "Issuance (repayment) of debt": -7120000.0,
        "Issuance (buybacks) of shares": 271000.0,
        "Dividend payments": 0.0,
        "Financing Cash Flow": -6849000.0,
        "Effect of forex changes on cash": NaN,
        "Net cash flow / Change in cash": NaN,
        "Free Cash Flow": NaN,
        "Net Cash/Marketcap": NaN
    }
}