{
    "2019": {
        "Revenue": 4731000000.0,
        "Revenue Growth": -0.0213074058750517,
        "Cost of Revenue": 1050000000.0,
        "Gross Profit": 3681000000.0,
        "R&D Expenses": 913000000.0,
        "SG&A Expense": 1940000000.0,
        "Operating Expenses": 3301000000.0,
        "Operating Income": 380000000.0,
        "Interest Expense": 0.0,
        "Earnings before Tax": 108000000.0,
        "Income Tax Expense": 92000000.0,
        "Net Income - Non-Controlling int": 0.0,
        "Net Income - Discontinued ops": 0.0,
        "Net Income": 31000000.0,
        "Preferred Dividends": 0.0,
        "Net Income Com": 31000000.0,
        "EPS": 0.05,
        "EPS Diluted": 0.05,
        "Weighted Average Shs Out": 632000000.0,
        "Weighted Average Shs Out (Dil)": 661000000.0,
        "Dividend per Share": 0.328290468986,
        "Gross Margin": 0.778059606848,
        "EBITDA Margin": 0.210314943986,
        "EBIT Margin": 0.0803212851406,
        "Profit Margin": 0.00655252589305,
        "Free Cash Flow margin": 0.272246882266,
        "EBITDA": 995000000.0,
        "EBIT": 380000000.0,
        "Consolidated Income": 31000000.0,
        "Earnings Before Tax Margin": 0.0228281547242,
        "Net Profit Margin": 0.00655252589305
    },
    "2018": {
        "Revenue": 4834000000.0,
        "Revenue Growth": 0.202786762876337,
        "Cost of Revenue": 1032000000.0,
        "Gross Profit": 3802000000.0,
        "R&D Expenses": 956000000.0,
        "SG&A Expense": 2167000000.0,
        "Operating Expenses": 3753000000.0,
        "Operating Income": 49000000.0,
        "Interest Expense": 0.0,
        "Earnings before Tax": 437000000.0,
        "Income Tax Expense": -690000000.0,
        "Net Income - Non-Controlling int": 0.0,
        "Net Income - Discontinued ops": 0.0,
        "Net Income": 1138000000.0,
        "Preferred Dividends": 0.0,
        "Net Income Com": 1138000000.0,
        "EPS": 1.85,
        "EPS Diluted": 1.7,
        "Weighted Average Shs Out": 616000000.0,
        "Weighted Average Shs Out (Dil)": 668000000.0,
        "Dividend per Share": 0.315868263473,
        "Gross Margin": 0.786512205213,
        "EBITDA Margin": 0.142532064543,
        "EBIT Margin": 0.010136532892,
        "Profit Margin": 0.235415804717,
        "Free Cash Flow margin": 0.167149358709,
        "EBITDA": 689000000.0,
        "EBIT": 49000000.0,
        "Consolidated Income": 1138000000.0,
        "Earnings Before Tax Margin": 0.0904013239553,
        "Net Profit Margin": 0.235415804717
    },
    "2017": {
        "Revenue": 4019000000.0,
        "Revenue Growth": 0.116388888888889,
        "Cost of Revenue": 853000000.0,
        "Gross Profit": 3166000000.0,
        "R&D Expenses": 823000000.0,
        "SG&A Expense": 2023000000.0,
        "Operating Expenses": 3266000000.0,
        "Operating Income": -100000000.0,
        "Interest Expense": 0.0,
        "Earnings before Tax": -262000000.0,
        "Income Tax Expense": -26000000.0,
        "Net Income - Non-Controlling int": 0.0,
        "Net Income - Discontinued ops": 0.0,
        "Net Income": -106000000.0,
        "Preferred Dividends": 0.0,
        "Net Income Com": -106000000.0,
        "EPS": -0.17,
        "EPS Diluted": -0.17,
        "Weighted Average Shs Out": 618000000.0,
        "Weighted Average Shs Out (Dil)": 618000000.0,
        "Dividend per Share": 0.359223300971,
        "Gross Margin": 0.787758148793,
        "EBITDA Margin": 0.106991789002,
        "EBIT Margin": -0.0248818113959,
        "Profit Margin": -0.0263747200796,
        "Free Cash Flow margin": -0.072157253048,
        "EBITDA": 430000000.0,
        "EBIT": -100000000.0,
        "Consolidated Income": -106000000.0,
        "Earnings Before Tax Margin": -0.0651903458572,
        "Net Profit Margin": -0.0263747200796
    },
    "2016": {
        "Revenue": 3600000000.0,
        "Revenue Growth": -0.446834665027658,
        "Cost of Revenue": 615000000.0,
        "Gross Profit": 2985000000.0,
        "R&D Expenses": 748000000.0,
        "SG&A Expense": 1587000000.0,
        "Operating Expenses": 2528000000.0,
        "Operating Income": 457000000.0,
        "Interest Expense": 0.0,
        "Earnings before Tax": 392000000.0,
        "Income Tax Expense": 1213000000.0,
        "Net Income - Non-Controlling int": 0.0,
        "Net Income - Discontinued ops": 0.0,
        "Net Income": 2488000000.0,
        "Preferred Dividends": 0.0,
        "Net Income Com": 2488000000.0,
        "EPS": 3.71,
        "EPS Diluted": 3.71,
        "Weighted Average Shs Out": 670000000.0,
        "Weighted Average Shs Out (Dil)": 670000000.0,
        "Dividend per Share": 4.5223880597,
        "Gross Margin": 0.829166666667,
        "EBITDA Margin": 0.211388888889,
        "EBIT Margin": 0.126944444444,
        "Profit Margin": 0.691111111111,
        "Free Cash Flow margin": 0.145555555556,
        "EBITDA": 761000000.0,
        "EBIT": 457000000.0,
        "Consolidated Income": 2488000000.0,
        "Earnings Before Tax Margin": 0.108888888889,
        "Net Profit Margin": 0.691111111111
    },
    "2015": {
        "Revenue": 6508000000.0,
        "Revenue Growth": -0.0251647693229479,
        "Cost of Revenue": 1153000000.0,
        "Gross Profit": 5355000000.0,
        "R&D Expenses": 1144000000.0,
        "SG&A Expense": 2702000000.0,
        "Operating Expenses": 4206000000.0,
        "Operating Income": 1149000000.0,
        "Interest Expense": 0.0,
        "Earnings before Tax": 1093000000.0,
        "Income Tax Expense": 215000000.0,
        "Net Income - Non-Controlling int": 0.0,
        "Net Income - Discontinued ops": 0.0,
        "Net Income": 878000000.0,
        "Preferred Dividends": 0.0,
        "Net Income Com": 878000000.0,
        "EPS": 1.27,
        "EPS Diluted": 1.26,
        "Weighted Average Shs Out": 689000000.0,
        "Weighted Average Shs Out (Dil)": 696000000.0,
        "Dividend per Share": 0.593390804598,
        "Gross Margin": 0.822833435771,
        "EBITDA Margin": 0.244622003688,
        "EBIT Margin": 0.176551936079,
        "Profit Margin": 0.134910878918,
        "Free Cash Flow margin": 0.143054701905,
        "EBITDA": 1592000000.0,
        "EBIT": 1149000000.0,
        "Consolidated Income": 878000000.0,
        "Earnings Before Tax Margin": 0.167947141979,
        "Net Profit Margin": 0.134910878918
    },
    "2014": {
        "Revenue": 6676000000.0,
        "Revenue Growth": -0.0333043730089777,
        "Cost of Revenue": 1149000000.0,
        "Gross Profit": 5527000000.0,
        "R&D Expenses": 1038000000.0,
        "SG&A Expense": 2880000000.0,
        "Operating Expenses": 4344000000.0,
        "Operating Income": 1183000000.0,
        "Interest Expense": 2000000.0,
        "Earnings before Tax": 890000000.0,
        "Income Tax Expense": 258000000.0,
        "Net Income - Non-Controlling int": 0.0,
        "Net Income - Discontinued ops": 0.0,
        "Net Income": 898000000.0,
        "Preferred Dividends": 0.0,
        "Net Income Com": 898000000.0,
        "EPS": 1.29,
        "EPS Diluted": 1.28,
        "Weighted Average Shs Out": 696000000.0,
        "Weighted Average Shs Out (Dil)": 704000000.0,
        "Dividend per Share": 0.59375,
        "Gross Margin": 0.827890952666,
        "EBITDA Margin": 0.251797483523,
        "EBIT Margin": 0.177201917316,
        "Profit Margin": 0.134511683643,
        "Free Cash Flow margin": 0.152935889754,
        "EBITDA": 1681000000.0,
        "EBIT": 1183000000.0,
        "Consolidated Income": 898000000.0,
        "Earnings Before Tax Margin": 0.133313361294,
        "Net Profit Margin": 0.134511683643
    },
    "2013": {
        "Revenue": 6906000000.0,
        "Revenue Growth": 0.0261515601783061,
        "Cost of Revenue": 1175000000.0,
        "Gross Profit": 5731000000.0,
        "R&D Expenses": 1012000000.0,
        "SG&A Expense": 3185000000.0,
        "Operating Expenses": 4608000000.0,
        "Operating Income": 1123000000.0,
        "Interest Expense": 10000000.0,
        "Earnings before Tax": 787000000.0,
        "Income Tax Expense": 214000000.0,
        "Net Income - Non-Controlling int": 0.0,
        "Net Income - Discontinued ops": 0.0,
        "Net Income": 765000000.0,
        "Preferred Dividends": 0.0,
        "Net Income Com": 765000000.0,
        "EPS": 1.09,
        "EPS Diluted": 1.08,
        "Weighted Average Shs Out": 701000000.0,
        "Weighted Average Shs Out (Dil)": 711000000.0,
        "Dividend per Share": 0.0,
        "Gross Margin": 0.829858094411,
        "EBITDA Margin": 0.263683753258,
        "EBIT Margin": 0.162612221257,
        "Profit Margin": 0.11077324066,
        "Free Cash Flow margin": 0.182015638575,
        "EBITDA": 1821000000.0,
        "EBIT": 1123000000.0,
        "Consolidated Income": 765000000.0,
        "Earnings Before Tax Margin": 0.113958876339,
        "Net Profit Margin": 0.11077324066
    },
    "2012": {
        "Revenue": 6730000000.0,
        "Revenue Growth": 0.0872374798061389,
        "Cost of Revenue": 1082000000.0,
        "Gross Profit": 5648000000.0,
        "R&D Expenses": 969000000.0,
        "SG&A Expense": 3251000000.0,
        "Operating Expenses": 4569000000.0,
        "Operating Income": 1079000000.0,
        "Interest Expense": 41000000.0,
        "Earnings before Tax": 1176000000.0,
        "Income Tax Expense": 274000000.0,
        "Net Income - Non-Controlling int": 0.0,
        "Net Income - Discontinued ops": 0.0,
        "Net Income": 1172000000.0,
        "Preferred Dividends": 0.0,
        "Net Income Com": 1172000000.0,
        "EPS": 1.58,
        "EPS Diluted": 1.57,
        "Weighted Average Shs Out": 741000000.0,
        "Weighted Average Shs Out (Dil)": 748000000.0,
        "Dividend per Share": 0.0,
        "Gross Margin": 0.839227340267,
        "EBITDA Margin": 0.266121842496,
        "EBIT Margin": 0.160326894502,
        "Profit Margin": 0.174145616642,
        "Free Cash Flow margin": 0.239970282318,
        "EBITDA": 1791000000.0,
        "EBIT": 1079000000.0,
        "Consolidated Income": 1172000000.0,
        "Earnings Before Tax Margin": 0.174739970282,
        "Net Profit Margin": 0.174145616642
    },
    "2011": {
        "Revenue": 6190000000.0,
        "Revenue Growth": 0.0,
        "Cost of Revenue": 1045000000.0,
        "Gross Profit": 5145000000.0,
        "R&D Expenses": 862000000.0,
        "SG&A Expense": 3012000000.0,
        "Operating Expenses": 4265000000.0,
        "Operating Income": 880000000.0,
        "Interest Expense": 0.0,
        "Earnings before Tax": 729000000.0,
        "Income Tax Expense": 105000000.0,
        "Net Income - Non-Controlling int": 0.0,
        "Net Income - Discontinued ops": 0.0,
        "Net Income": 597000000.0,
        "Preferred Dividends": 0.0,
        "Net Income Com": 597000000.0,
        "EPS": 0.77,
        "EPS Diluted": 0.76,
        "Weighted Average Shs Out": 778000000.0,
        "Weighted Average Shs Out (Dil)": 786000000.0,
        "Dividend per Share": 0.0,
        "Gross Margin": 0.831179321486,
        "EBITDA Margin": 0.262197092084,
        "EBIT Margin": 0.142164781906,
        "Profit Margin": 0.0964458804523,
        "Free Cash Flow margin": 0.246526655897,
        "EBITDA": 1623000000.0,
        "EBIT": 880000000.0,
        "Consolidated Income": 597000000.0,
        "Earnings Before Tax Margin": 0.117770597738,
        "Net Profit Margin": 0.0964458804523
    },
    "2010": {
        "Revenue": 0.0,
        "Revenue Growth": 0.0,
        "Cost of Revenue": 0.0,
        "Gross Profit": 0.0,
        "R&D Expenses": 0.0,
        "SG&A Expense": 0.0,
        "Operating Expenses": 0.0,
        "Operating Income": 0.0,
        "Interest Expense": 0.0,
        "Earnings before Tax": 687000000.0,
        "Income Tax Expense": 0.0,
        "Net Income - Non-Controlling int": 0.0,
        "Net Income - Discontinued ops": 0.0,
        "Net Income": 714000000.0,
        "Preferred Dividends": 0.0,
        "Net Income Com": 714000000.0,
        "EPS": 0.0,
        "EPS Diluted": 0.0,
        "Weighted Average Shs Out": 0.0,
        "Weighted Average Shs Out (Dil)": 0.0,
        "Dividend per Share": 0.0,
        "Gross Margin": 0.0,
        "EBITDA Margin": 0.0,
        "EBIT Margin": 0.0,
        "Profit Margin": 0.0,
        "Free Cash Flow margin": 0.0,
        "EBITDA": 0.0,
        "EBIT": 0.0,
        "Consolidated Income": 714000000.0,
        "Earnings Before Tax Margin": 0.0,
        "Net Profit Margin": 0.0
    }
}